signinghubapi/__init__.py
signinghubapi/classes.py
signinghubapi/signinghubapi.py
signinghubapi/utils.py
signinghubapi-0.1.5.dist-info/LICENSE
signinghubapi-0.1.5.dist-info/METADATA
signinghubapi-0.1.5.dist-info/WHEEL
signinghubapi-0.1.5.dist-info/top_level.txt
signinghubapi-0.1.5.dist-info/RECORD
