Metadata-Version: 2.1
Name: signinghubapi
Version: 0.1.5
Summary: Package with default calls for the SigningHub API
Home-page: https://github.com/erwinmintiens/signinghubapi
Author: Erwin Mintiens
Author-email: erwin.mintiens@protonmail.com
Keywords: SigningHub,API
Classifier: Development Status :: 4 - Beta
Classifier: Intended Audience :: Developers
Classifier: Programming Language :: Python :: 3
Classifier: Operating System :: Unix
Classifier: Operating System :: MacOS :: MacOS X
Classifier: Operating System :: Microsoft :: Windows
Classifier: License :: OSI Approved :: MIT License
License-File: LICENSE
Requires-Dist: requests
